[{"name":"at_server_spec","qualifiedName":"at_server_spec","href":"at_server_spec/at_server_spec-library.html","type":"library","overriddenDepth":0,"packageName":"at_server_spec"},{"name":"AtClientConnection","qualifiedName":"at_server_spec.AtClientConnection","href":"at_server_spec/AtClientConnection-class.html","type":"class","overriddenDepth":0,"packageName":"at_server_spec","enclosedBy":{"name":"at_server_spec","type":"library"}},{"name":"AtClientConnection","qualifiedName":"at_server_spec.AtClientConnection.AtClientConnection","href":"at_server_spec/AtClientConnection/AtClientConnection.html","type":"constructor","overriddenDepth":0,"packageName":"at_server_spec","enclosedBy":{"name":"AtClientConnection","type":"class"}},{"name":"getSocket","qualifiedName":"at_server_spec.AtClientConnection.getSocket","href":"at_server_spec/AtClientConnection/getSocket.html","type":"method","overriddenDepth":0,"packageName":"at_server_spec","enclosedBy":{"name":"AtClientConnection","type":"class"}},{"name":"AtConnection","qualifiedName":"at_server_spec.AtConnection","href":"at_server_spec/AtConnection-class.html","type":"class","overriddenDepth":0,"packageName":"at_server_spec","enclosedBy":{"name":"at_server_spec","type":"library"}},{"name":"AtConnection","qualifiedName":"at_server_spec.AtConnection.AtConnection","href":"at_server_spec/AtConnection/AtConnection.html","type":"constructor","overriddenDepth":0,"packageName":"at_server_spec","enclosedBy":{"name":"AtConnection","type":"class"}},{"name":"close","qualifiedName":"at_server_spec.AtConnection.close","href":"at_server_spec/AtConnection/close.html","type":"method","overriddenDepth":0,"packageName":"at_server_spec","enclosedBy":{"name":"AtConnection","type":"class"}},{"name":"getMetaData","qualifiedName":"at_server_spec.AtConnection.getMetaData","href":"at_server_spec/AtConnection/getMetaData.html","type":"method","overriddenDepth":0,"packageName":"at_server_spec","enclosedBy":{"name":"AtConnection","type":"class"}},{"name":"getSocket","qualifiedName":"at_server_spec.AtConnection.getSocket","href":"at_server_spec/AtConnection/getSocket.html","type":"method","overriddenDepth":0,"packageName":"at_server_spec","enclosedBy":{"name":"AtConnection","type":"class"}},{"name":"isInValid","qualifiedName":"at_server_spec.AtConnection.isInValid","href":"at_server_spec/AtConnection/isInValid.html","type":"method","overriddenDepth":0,"packageName":"at_server_spec","enclosedBy":{"name":"AtConnection","type":"class"}},{"name":"write","qualifiedName":"at_server_spec.AtConnection.write","href":"at_server_spec/AtConnection/write.html","type":"method","overriddenDepth":0,"packageName":"at_server_spec","enclosedBy":{"name":"AtConnection","type":"class"}},{"name":"AtConnectionMetaData","qualifiedName":"at_server_spec.AtConnectionMetaData","href":"at_server_spec/AtConnectionMetaData-class.html","type":"class","overriddenDepth":0,"packageName":"at_server_spec","enclosedBy":{"name":"at_server_spec","type":"library"}},{"name":"AtConnectionMetaData","qualifiedName":"at_server_spec.AtConnectionMetaData.AtConnectionMetaData","href":"at_server_spec/AtConnectionMetaData/AtConnectionMetaData.html","type":"constructor","overriddenDepth":0,"packageName":"at_server_spec","enclosedBy":{"name":"AtConnectionMetaData","type":"class"}},{"name":"created","qualifiedName":"at_server_spec.AtConnectionMetaData.created","href":"at_server_spec/AtConnectionMetaData/created.html","type":"property","overriddenDepth":0,"packageName":"at_server_spec","enclosedBy":{"name":"AtConnectionMetaData","type":"class"}},{"name":"isAuthenticated","qualifiedName":"at_server_spec.AtConnectionMetaData.isAuthenticated","href":"at_server_spec/AtConnectionMetaData/isAuthenticated.html","type":"property","overriddenDepth":0,"packageName":"at_server_spec","enclosedBy":{"name":"AtConnectionMetaData","type":"class"}},{"name":"isClosed","qualifiedName":"at_server_spec.AtConnectionMetaData.isClosed","href":"at_server_spec/AtConnectionMetaData/isClosed.html","type":"property","overriddenDepth":0,"packageName":"at_server_spec","enclosedBy":{"name":"AtConnectionMetaData","type":"class"}},{"name":"isCreated","qualifiedName":"at_server_spec.AtConnectionMetaData.isCreated","href":"at_server_spec/AtConnectionMetaData/isCreated.html","type":"property","overriddenDepth":0,"packageName":"at_server_spec","enclosedBy":{"name":"AtConnectionMetaData","type":"class"}},{"name":"isListening","qualifiedName":"at_server_spec.AtConnectionMetaData.isListening","href":"at_server_spec/AtConnectionMetaData/isListening.html","type":"property","overriddenDepth":0,"packageName":"at_server_spec","enclosedBy":{"name":"AtConnectionMetaData","type":"class"}},{"name":"isPolAuthenticated","qualifiedName":"at_server_spec.AtConnectionMetaData.isPolAuthenticated","href":"at_server_spec/AtConnectionMetaData/isPolAuthenticated.html","type":"property","overriddenDepth":0,"packageName":"at_server_spec","enclosedBy":{"name":"AtConnectionMetaData","type":"class"}},{"name":"isStale","qualifiedName":"at_server_spec.AtConnectionMetaData.isStale","href":"at_server_spec/AtConnectionMetaData/isStale.html","type":"property","overriddenDepth":0,"packageName":"at_server_spec","enclosedBy":{"name":"AtConnectionMetaData","type":"class"}},{"name":"isStream","qualifiedName":"at_server_spec.AtConnectionMetaData.isStream","href":"at_server_spec/AtConnectionMetaData/isStream.html","type":"property","overriddenDepth":0,"packageName":"at_server_spec","enclosedBy":{"name":"AtConnectionMetaData","type":"class"}},{"name":"lastAccessed","qualifiedName":"at_server_spec.AtConnectionMetaData.lastAccessed","href":"at_server_spec/AtConnectionMetaData/lastAccessed.html","type":"property","overriddenDepth":0,"packageName":"at_server_spec","enclosedBy":{"name":"AtConnectionMetaData","type":"class"}},{"name":"sessionID","qualifiedName":"at_server_spec.AtConnectionMetaData.sessionID","href":"at_server_spec/AtConnectionMetaData/sessionID.html","type":"property","overriddenDepth":0,"packageName":"at_server_spec","enclosedBy":{"name":"AtConnectionMetaData","type":"class"}},{"name":"streamId","qualifiedName":"at_server_spec.AtConnectionMetaData.streamId","href":"at_server_spec/AtConnectionMetaData/streamId.html","type":"property","overriddenDepth":0,"packageName":"at_server_spec","enclosedBy":{"name":"AtConnectionMetaData","type":"class"}},{"name":"AtRootServer","qualifiedName":"at_server_spec.AtRootServer","href":"at_server_spec/AtRootServer-class.html","type":"class","overriddenDepth":0,"packageName":"at_server_spec","enclosedBy":{"name":"at_server_spec","type":"library"}},{"name":"AtRootServer","qualifiedName":"at_server_spec.AtRootServer.AtRootServer","href":"at_server_spec/AtRootServer/AtRootServer.html","type":"constructor","overriddenDepth":0,"packageName":"at_server_spec","enclosedBy":{"name":"AtRootServer","type":"class"}},{"name":"setServerContext","qualifiedName":"at_server_spec.AtRootServer.setServerContext","href":"at_server_spec/AtRootServer/setServerContext.html","type":"method","overriddenDepth":0,"packageName":"at_server_spec","enclosedBy":{"name":"AtRootServer","type":"class"}},{"name":"AtSecondaryServer","qualifiedName":"at_server_spec.AtSecondaryServer","href":"at_server_spec/AtSecondaryServer-class.html","type":"class","overriddenDepth":0,"packageName":"at_server_spec","enclosedBy":{"name":"at_server_spec","type":"library"}},{"name":"AtSecondaryServer","qualifiedName":"at_server_spec.AtSecondaryServer.AtSecondaryServer","href":"at_server_spec/AtSecondaryServer/AtSecondaryServer.html","type":"constructor","overriddenDepth":0,"packageName":"at_server_spec","enclosedBy":{"name":"AtSecondaryServer","type":"class"}},{"name":"getMetrics","qualifiedName":"at_server_spec.AtSecondaryServer.getMetrics","href":"at_server_spec/AtSecondaryServer/getMetrics.html","type":"method","overriddenDepth":0,"packageName":"at_server_spec","enclosedBy":{"name":"AtSecondaryServer","type":"class"}},{"name":"setExecutor","qualifiedName":"at_server_spec.AtSecondaryServer.setExecutor","href":"at_server_spec/AtSecondaryServer/setExecutor.html","type":"method","overriddenDepth":0,"packageName":"at_server_spec","enclosedBy":{"name":"AtSecondaryServer","type":"class"}},{"name":"setServerContext","qualifiedName":"at_server_spec.AtSecondaryServer.setServerContext","href":"at_server_spec/AtSecondaryServer/setServerContext.html","type":"method","overriddenDepth":0,"packageName":"at_server_spec","enclosedBy":{"name":"AtSecondaryServer","type":"class"}},{"name":"setVerbHandlerManager","qualifiedName":"at_server_spec.AtSecondaryServer.setVerbHandlerManager","href":"at_server_spec/AtSecondaryServer/setVerbHandlerManager.html","type":"method","overriddenDepth":0,"packageName":"at_server_spec","enclosedBy":{"name":"AtSecondaryServer","type":"class"}},{"name":"AtSecurityContext","qualifiedName":"at_server_spec.AtSecurityContext","href":"at_server_spec/AtSecurityContext-class.html","type":"class","overriddenDepth":0,"packageName":"at_server_spec","enclosedBy":{"name":"at_server_spec","type":"library"}},{"name":"AtSecurityContext","qualifiedName":"at_server_spec.AtSecurityContext.AtSecurityContext","href":"at_server_spec/AtSecurityContext/AtSecurityContext.html","type":"constructor","overriddenDepth":0,"packageName":"at_server_spec","enclosedBy":{"name":"AtSecurityContext","type":"class"}},{"name":"bundle","qualifiedName":"at_server_spec.AtSecurityContext.bundle","href":"at_server_spec/AtSecurityContext/bundle.html","type":"method","overriddenDepth":0,"packageName":"at_server_spec","enclosedBy":{"name":"AtSecurityContext","type":"class"}},{"name":"privateKeyPath","qualifiedName":"at_server_spec.AtSecurityContext.privateKeyPath","href":"at_server_spec/AtSecurityContext/privateKeyPath.html","type":"method","overriddenDepth":0,"packageName":"at_server_spec","enclosedBy":{"name":"AtSecurityContext","type":"class"}},{"name":"publicKeyPath","qualifiedName":"at_server_spec.AtSecurityContext.publicKeyPath","href":"at_server_spec/AtSecurityContext/publicKeyPath.html","type":"method","overriddenDepth":0,"packageName":"at_server_spec","enclosedBy":{"name":"AtSecurityContext","type":"class"}},{"name":"trustedCertificatePath","qualifiedName":"at_server_spec.AtSecurityContext.trustedCertificatePath","href":"at_server_spec/AtSecurityContext/trustedCertificatePath.html","type":"method","overriddenDepth":0,"packageName":"at_server_spec","enclosedBy":{"name":"AtSecurityContext","type":"class"}},{"name":"AtServer","qualifiedName":"at_server_spec.AtServer","href":"at_server_spec/AtServer-class.html","type":"class","overriddenDepth":0,"packageName":"at_server_spec","enclosedBy":{"name":"at_server_spec","type":"library"}},{"name":"AtServer","qualifiedName":"at_server_spec.AtServer.AtServer","href":"at_server_spec/AtServer/AtServer.html","type":"constructor","overriddenDepth":0,"packageName":"at_server_spec","enclosedBy":{"name":"AtServer","type":"class"}},{"name":"isRunning","qualifiedName":"at_server_spec.AtServer.isRunning","href":"at_server_spec/AtServer/isRunning.html","type":"method","overriddenDepth":0,"packageName":"at_server_spec","enclosedBy":{"name":"AtServer","type":"class"}},{"name":"pause","qualifiedName":"at_server_spec.AtServer.pause","href":"at_server_spec/AtServer/pause.html","type":"method","overriddenDepth":0,"packageName":"at_server_spec","enclosedBy":{"name":"AtServer","type":"class"}},{"name":"resume","qualifiedName":"at_server_spec.AtServer.resume","href":"at_server_spec/AtServer/resume.html","type":"method","overriddenDepth":0,"packageName":"at_server_spec","enclosedBy":{"name":"AtServer","type":"class"}},{"name":"start","qualifiedName":"at_server_spec.AtServer.start","href":"at_server_spec/AtServer/start.html","type":"method","overriddenDepth":0,"packageName":"at_server_spec","enclosedBy":{"name":"AtServer","type":"class"}},{"name":"stop","qualifiedName":"at_server_spec.AtServer.stop","href":"at_server_spec/AtServer/stop.html","type":"method","overriddenDepth":0,"packageName":"at_server_spec","enclosedBy":{"name":"AtServer","type":"class"}},{"name":"AtServerContext","qualifiedName":"at_server_spec.AtServerContext","href":"at_server_spec/AtServerContext-class.html","type":"class","overriddenDepth":0,"packageName":"at_server_spec","enclosedBy":{"name":"at_server_spec","type":"library"}},{"name":"AtServerContext","qualifiedName":"at_server_spec.AtServerContext.AtServerContext","href":"at_server_spec/AtServerContext/AtServerContext.html","type":"constructor","overriddenDepth":0,"packageName":"at_server_spec","enclosedBy":{"name":"AtServerContext","type":"class"}},{"name":"ConnectionMetrics","qualifiedName":"at_server_spec.ConnectionMetrics","href":"at_server_spec/ConnectionMetrics-class.html","type":"class","overriddenDepth":0,"packageName":"at_server_spec","enclosedBy":{"name":"at_server_spec","type":"library"}},{"name":"ConnectionMetrics","qualifiedName":"at_server_spec.ConnectionMetrics.ConnectionMetrics","href":"at_server_spec/ConnectionMetrics/ConnectionMetrics.html","type":"constructor","overriddenDepth":0,"packageName":"at_server_spec","enclosedBy":{"name":"ConnectionMetrics","type":"class"}},{"name":"getInboundConnections","qualifiedName":"at_server_spec.ConnectionMetrics.getInboundConnections","href":"at_server_spec/ConnectionMetrics/getInboundConnections.html","type":"method","overriddenDepth":0,"packageName":"at_server_spec","enclosedBy":{"name":"ConnectionMetrics","type":"class"}},{"name":"getOutboundConnections","qualifiedName":"at_server_spec.ConnectionMetrics.getOutboundConnections","href":"at_server_spec/ConnectionMetrics/getOutboundConnections.html","type":"method","overriddenDepth":0,"packageName":"at_server_spec","enclosedBy":{"name":"ConnectionMetrics","type":"class"}},{"name":"InboundConnection","qualifiedName":"at_server_spec.InboundConnection","href":"at_server_spec/InboundConnection-class.html","type":"class","overriddenDepth":0,"packageName":"at_server_spec","enclosedBy":{"name":"at_server_spec","type":"library"}},{"name":"InboundConnection","qualifiedName":"at_server_spec.InboundConnection.InboundConnection","href":"at_server_spec/InboundConnection/InboundConnection.html","type":"constructor","overriddenDepth":0,"packageName":"at_server_spec","enclosedBy":{"name":"InboundConnection","type":"class"}},{"name":"acceptRequests","qualifiedName":"at_server_spec.InboundConnection.acceptRequests","href":"at_server_spec/InboundConnection/acceptRequests.html","type":"method","overriddenDepth":0,"packageName":"at_server_spec","enclosedBy":{"name":"InboundConnection","type":"class"}},{"name":"equals","qualifiedName":"at_server_spec.InboundConnection.equals","href":"at_server_spec/InboundConnection/equals.html","type":"method","overriddenDepth":0,"packageName":"at_server_spec","enclosedBy":{"name":"InboundConnection","type":"class"}},{"name":"initiatedBy","qualifiedName":"at_server_spec.InboundConnection.initiatedBy","href":"at_server_spec/InboundConnection/initiatedBy.html","type":"property","overriddenDepth":0,"packageName":"at_server_spec","enclosedBy":{"name":"InboundConnection","type":"class"}},{"name":"isMonitor","qualifiedName":"at_server_spec.InboundConnection.isMonitor","href":"at_server_spec/InboundConnection/isMonitor.html","type":"property","overriddenDepth":0,"packageName":"at_server_spec","enclosedBy":{"name":"InboundConnection","type":"class"}},{"name":"isStream","qualifiedName":"at_server_spec.InboundConnection.isStream","href":"at_server_spec/InboundConnection/isStream.html","type":"property","overriddenDepth":0,"packageName":"at_server_spec","enclosedBy":{"name":"InboundConnection","type":"class"}},{"name":"receiverSocket","qualifiedName":"at_server_spec.InboundConnection.receiverSocket","href":"at_server_spec/InboundConnection/receiverSocket.html","type":"property","overriddenDepth":0,"packageName":"at_server_spec","enclosedBy":{"name":"InboundConnection","type":"class"}},{"name":"at_verb_spec","qualifiedName":"at_verb_spec","href":"at_verb_spec/at_verb_spec-library.html","type":"library","overriddenDepth":0,"packageName":"at_server_spec"},{"name":"Response","qualifiedName":"at_verb_spec.Response","href":"at_verb_spec/Response-class.html","type":"class","overriddenDepth":0,"packageName":"at_server_spec","enclosedBy":{"name":"at_verb_spec","type":"library"}},{"name":"Response","qualifiedName":"at_verb_spec.Response.Response","href":"at_verb_spec/Response/Response.html","type":"constructor","overriddenDepth":0,"packageName":"at_server_spec","enclosedBy":{"name":"Response","type":"class"}},{"name":"atException","qualifiedName":"at_verb_spec.Response.atException","href":"at_verb_spec/Response/atException.html","type":"property","overriddenDepth":0,"packageName":"at_server_spec","enclosedBy":{"name":"Response","type":"class"}},{"name":"data","qualifiedName":"at_verb_spec.Response.data","href":"at_verb_spec/Response/data.html","type":"property","overriddenDepth":0,"packageName":"at_server_spec","enclosedBy":{"name":"Response","type":"class"}},{"name":"errorCode","qualifiedName":"at_verb_spec.Response.errorCode","href":"at_verb_spec/Response/errorCode.html","type":"property","overriddenDepth":0,"packageName":"at_server_spec","enclosedBy":{"name":"Response","type":"class"}},{"name":"errorMessage","qualifiedName":"at_verb_spec.Response.errorMessage","href":"at_verb_spec/Response/errorMessage.html","type":"property","overriddenDepth":0,"packageName":"at_server_spec","enclosedBy":{"name":"Response","type":"class"}},{"name":"isError","qualifiedName":"at_verb_spec.Response.isError","href":"at_verb_spec/Response/isError.html","type":"property","overriddenDepth":0,"packageName":"at_server_spec","enclosedBy":{"name":"Response","type":"class"}},{"name":"isStream","qualifiedName":"at_verb_spec.Response.isStream","href":"at_verb_spec/Response/isStream.html","type":"property","overriddenDepth":0,"packageName":"at_server_spec","enclosedBy":{"name":"Response","type":"class"}},{"name":"toString","qualifiedName":"at_verb_spec.Response.toString","href":"at_verb_spec/Response/toString.html","type":"method","overriddenDepth":1,"packageName":"at_server_spec","enclosedBy":{"name":"Response","type":"class"}},{"name":"type","qualifiedName":"at_verb_spec.Response.type","href":"at_verb_spec/Response/type.html","type":"property","overriddenDepth":0,"packageName":"at_server_spec","enclosedBy":{"name":"Response","type":"class"}},{"name":"VerbExecutor","qualifiedName":"at_verb_spec.VerbExecutor","href":"at_verb_spec/VerbExecutor-class.html","type":"class","overriddenDepth":0,"packageName":"at_server_spec","enclosedBy":{"name":"at_verb_spec","type":"library"}},{"name":"VerbExecutor","qualifiedName":"at_verb_spec.VerbExecutor.VerbExecutor","href":"at_verb_spec/VerbExecutor/VerbExecutor.html","type":"constructor","overriddenDepth":0,"packageName":"at_server_spec","enclosedBy":{"name":"VerbExecutor","type":"class"}},{"name":"execute","qualifiedName":"at_verb_spec.VerbExecutor.execute","href":"at_verb_spec/VerbExecutor/execute.html","type":"method","overriddenDepth":0,"packageName":"at_server_spec","enclosedBy":{"name":"VerbExecutor","type":"class"}},{"name":"VerbHandler","qualifiedName":"at_verb_spec.VerbHandler","href":"at_verb_spec/VerbHandler-class.html","type":"class","overriddenDepth":0,"packageName":"at_server_spec","enclosedBy":{"name":"at_verb_spec","type":"library"}},{"name":"VerbHandler","qualifiedName":"at_verb_spec.VerbHandler.VerbHandler","href":"at_verb_spec/VerbHandler/VerbHandler.html","type":"constructor","overriddenDepth":0,"packageName":"at_server_spec","enclosedBy":{"name":"VerbHandler","type":"class"}},{"name":"accept","qualifiedName":"at_verb_spec.VerbHandler.accept","href":"at_verb_spec/VerbHandler/accept.html","type":"method","overriddenDepth":0,"packageName":"at_server_spec","enclosedBy":{"name":"VerbHandler","type":"class"}},{"name":"process","qualifiedName":"at_verb_spec.VerbHandler.process","href":"at_verb_spec/VerbHandler/process.html","type":"method","overriddenDepth":0,"packageName":"at_server_spec","enclosedBy":{"name":"VerbHandler","type":"class"}},{"name":"VerbHandlerManager","qualifiedName":"at_verb_spec.VerbHandlerManager","href":"at_verb_spec/VerbHandlerManager-class.html","type":"class","overriddenDepth":0,"packageName":"at_server_spec","enclosedBy":{"name":"at_verb_spec","type":"library"}},{"name":"VerbHandlerManager","qualifiedName":"at_verb_spec.VerbHandlerManager.VerbHandlerManager","href":"at_verb_spec/VerbHandlerManager/VerbHandlerManager.html","type":"constructor","overriddenDepth":0,"packageName":"at_server_spec","enclosedBy":{"name":"VerbHandlerManager","type":"class"}},{"name":"getVerbHandler","qualifiedName":"at_verb_spec.VerbHandlerManager.getVerbHandler","href":"at_verb_spec/VerbHandlerManager/getVerbHandler.html","type":"method","overriddenDepth":0,"packageName":"at_server_spec","enclosedBy":{"name":"VerbHandlerManager","type":"class"}},{"name":"verbs","qualifiedName":"verbs","href":"verbs/verbs-library.html","type":"library","overriddenDepth":0,"packageName":"at_server_spec"},{"name":"Config","qualifiedName":"verbs.Config","href":"verbs/Config-class.html","type":"class","overriddenDepth":0,"packageName":"at_server_spec","enclosedBy":{"name":"verbs","type":"library"}},{"name":"Config","qualifiedName":"verbs.Config.Config","href":"verbs/Config/Config.html","type":"constructor","overriddenDepth":0,"packageName":"at_server_spec","enclosedBy":{"name":"Config","type":"class"}},{"name":"dependsOn","qualifiedName":"verbs.Config.dependsOn","href":"verbs/Config/dependsOn.html","type":"method","overriddenDepth":1,"packageName":"at_server_spec","enclosedBy":{"name":"Config","type":"class"}},{"name":"name","qualifiedName":"verbs.Config.name","href":"verbs/Config/name.html","type":"method","overriddenDepth":1,"packageName":"at_server_spec","enclosedBy":{"name":"Config","type":"class"}},{"name":"requiresAuth","qualifiedName":"verbs.Config.requiresAuth","href":"verbs/Config/requiresAuth.html","type":"method","overriddenDepth":1,"packageName":"at_server_spec","enclosedBy":{"name":"Config","type":"class"}},{"name":"syntax","qualifiedName":"verbs.Config.syntax","href":"verbs/Config/syntax.html","type":"method","overriddenDepth":1,"packageName":"at_server_spec","enclosedBy":{"name":"Config","type":"class"}},{"name":"usage","qualifiedName":"verbs.Config.usage","href":"verbs/Config/usage.html","type":"method","overriddenDepth":1,"packageName":"at_server_spec","enclosedBy":{"name":"Config","type":"class"}},{"name":"Cram","qualifiedName":"verbs.Cram","href":"verbs/Cram-class.html","type":"class","overriddenDepth":0,"packageName":"at_server_spec","enclosedBy":{"name":"verbs","type":"library"}},{"name":"Cram","qualifiedName":"verbs.Cram.Cram","href":"verbs/Cram/Cram.html","type":"constructor","overriddenDepth":0,"packageName":"at_server_spec","enclosedBy":{"name":"Cram","type":"class"}},{"name":"dependsOn","qualifiedName":"verbs.Cram.dependsOn","href":"verbs/Cram/dependsOn.html","type":"method","overriddenDepth":1,"packageName":"at_server_spec","enclosedBy":{"name":"Cram","type":"class"}},{"name":"name","qualifiedName":"verbs.Cram.name","href":"verbs/Cram/name.html","type":"method","overriddenDepth":1,"packageName":"at_server_spec","enclosedBy":{"name":"Cram","type":"class"}},{"name":"requiresAuth","qualifiedName":"verbs.Cram.requiresAuth","href":"verbs/Cram/requiresAuth.html","type":"method","overriddenDepth":1,"packageName":"at_server_spec","enclosedBy":{"name":"Cram","type":"class"}},{"name":"syntax","qualifiedName":"verbs.Cram.syntax","href":"verbs/Cram/syntax.html","type":"method","overriddenDepth":1,"packageName":"at_server_spec","enclosedBy":{"name":"Cram","type":"class"}},{"name":"usage","qualifiedName":"verbs.Cram.usage","href":"verbs/Cram/usage.html","type":"method","overriddenDepth":1,"packageName":"at_server_spec","enclosedBy":{"name":"Cram","type":"class"}},{"name":"Delete","qualifiedName":"verbs.Delete","href":"verbs/Delete-class.html","type":"class","overriddenDepth":0,"packageName":"at_server_spec","enclosedBy":{"name":"verbs","type":"library"}},{"name":"Delete","qualifiedName":"verbs.Delete.Delete","href":"verbs/Delete/Delete.html","type":"constructor","overriddenDepth":0,"packageName":"at_server_spec","enclosedBy":{"name":"Delete","type":"class"}},{"name":"dependsOn","qualifiedName":"verbs.Delete.dependsOn","href":"verbs/Delete/dependsOn.html","type":"method","overriddenDepth":1,"packageName":"at_server_spec","enclosedBy":{"name":"Delete","type":"class"}},{"name":"name","qualifiedName":"verbs.Delete.name","href":"verbs/Delete/name.html","type":"method","overriddenDepth":1,"packageName":"at_server_spec","enclosedBy":{"name":"Delete","type":"class"}},{"name":"requiresAuth","qualifiedName":"verbs.Delete.requiresAuth","href":"verbs/Delete/requiresAuth.html","type":"method","overriddenDepth":1,"packageName":"at_server_spec","enclosedBy":{"name":"Delete","type":"class"}},{"name":"syntax","qualifiedName":"verbs.Delete.syntax","href":"verbs/Delete/syntax.html","type":"method","overriddenDepth":1,"packageName":"at_server_spec","enclosedBy":{"name":"Delete","type":"class"}},{"name":"usage","qualifiedName":"verbs.Delete.usage","href":"verbs/Delete/usage.html","type":"method","overriddenDepth":1,"packageName":"at_server_spec","enclosedBy":{"name":"Delete","type":"class"}},{"name":"From","qualifiedName":"verbs.From","href":"verbs/From-class.html","type":"class","overriddenDepth":0,"packageName":"at_server_spec","enclosedBy":{"name":"verbs","type":"library"}},{"name":"From","qualifiedName":"verbs.From.From","href":"verbs/From/From.html","type":"constructor","overriddenDepth":0,"packageName":"at_server_spec","enclosedBy":{"name":"From","type":"class"}},{"name":"dependsOn","qualifiedName":"verbs.From.dependsOn","href":"verbs/From/dependsOn.html","type":"method","overriddenDepth":1,"packageName":"at_server_spec","enclosedBy":{"name":"From","type":"class"}},{"name":"name","qualifiedName":"verbs.From.name","href":"verbs/From/name.html","type":"method","overriddenDepth":1,"packageName":"at_server_spec","enclosedBy":{"name":"From","type":"class"}},{"name":"requiresAuth","qualifiedName":"verbs.From.requiresAuth","href":"verbs/From/requiresAuth.html","type":"method","overriddenDepth":1,"packageName":"at_server_spec","enclosedBy":{"name":"From","type":"class"}},{"name":"syntax","qualifiedName":"verbs.From.syntax","href":"verbs/From/syntax.html","type":"method","overriddenDepth":1,"packageName":"at_server_spec","enclosedBy":{"name":"From","type":"class"}},{"name":"usage","qualifiedName":"verbs.From.usage","href":"verbs/From/usage.html","type":"method","overriddenDepth":1,"packageName":"at_server_spec","enclosedBy":{"name":"From","type":"class"}},{"name":"LocalLookup","qualifiedName":"verbs.LocalLookup","href":"verbs/LocalLookup-class.html","type":"class","overriddenDepth":0,"packageName":"at_server_spec","enclosedBy":{"name":"verbs","type":"library"}},{"name":"LocalLookup","qualifiedName":"verbs.LocalLookup.LocalLookup","href":"verbs/LocalLookup/LocalLookup.html","type":"constructor","overriddenDepth":0,"packageName":"at_server_spec","enclosedBy":{"name":"LocalLookup","type":"class"}},{"name":"dependsOn","qualifiedName":"verbs.LocalLookup.dependsOn","href":"verbs/LocalLookup/dependsOn.html","type":"method","overriddenDepth":1,"packageName":"at_server_spec","enclosedBy":{"name":"LocalLookup","type":"class"}},{"name":"name","qualifiedName":"verbs.LocalLookup.name","href":"verbs/LocalLookup/name.html","type":"method","overriddenDepth":1,"packageName":"at_server_spec","enclosedBy":{"name":"LocalLookup","type":"class"}},{"name":"requiresAuth","qualifiedName":"verbs.LocalLookup.requiresAuth","href":"verbs/LocalLookup/requiresAuth.html","type":"method","overriddenDepth":1,"packageName":"at_server_spec","enclosedBy":{"name":"LocalLookup","type":"class"}},{"name":"syntax","qualifiedName":"verbs.LocalLookup.syntax","href":"verbs/LocalLookup/syntax.html","type":"method","overriddenDepth":1,"packageName":"at_server_spec","enclosedBy":{"name":"LocalLookup","type":"class"}},{"name":"usage","qualifiedName":"verbs.LocalLookup.usage","href":"verbs/LocalLookup/usage.html","type":"method","overriddenDepth":1,"packageName":"at_server_spec","enclosedBy":{"name":"LocalLookup","type":"class"}},{"name":"Lookup","qualifiedName":"verbs.Lookup","href":"verbs/Lookup-class.html","type":"class","overriddenDepth":0,"packageName":"at_server_spec","enclosedBy":{"name":"verbs","type":"library"}},{"name":"Lookup","qualifiedName":"verbs.Lookup.Lookup","href":"verbs/Lookup/Lookup.html","type":"constructor","overriddenDepth":0,"packageName":"at_server_spec","enclosedBy":{"name":"Lookup","type":"class"}},{"name":"dependsOn","qualifiedName":"verbs.Lookup.dependsOn","href":"verbs/Lookup/dependsOn.html","type":"method","overriddenDepth":1,"packageName":"at_server_spec","enclosedBy":{"name":"Lookup","type":"class"}},{"name":"name","qualifiedName":"verbs.Lookup.name","href":"verbs/Lookup/name.html","type":"method","overriddenDepth":1,"packageName":"at_server_spec","enclosedBy":{"name":"Lookup","type":"class"}},{"name":"requiresAuth","qualifiedName":"verbs.Lookup.requiresAuth","href":"verbs/Lookup/requiresAuth.html","type":"method","overriddenDepth":1,"packageName":"at_server_spec","enclosedBy":{"name":"Lookup","type":"class"}},{"name":"syntax","qualifiedName":"verbs.Lookup.syntax","href":"verbs/Lookup/syntax.html","type":"method","overriddenDepth":1,"packageName":"at_server_spec","enclosedBy":{"name":"Lookup","type":"class"}},{"name":"usage","qualifiedName":"verbs.Lookup.usage","href":"verbs/Lookup/usage.html","type":"method","overriddenDepth":1,"packageName":"at_server_spec","enclosedBy":{"name":"Lookup","type":"class"}},{"name":"Monitor","qualifiedName":"verbs.Monitor","href":"verbs/Monitor-class.html","type":"class","overriddenDepth":0,"packageName":"at_server_spec","enclosedBy":{"name":"verbs","type":"library"}},{"name":"Monitor","qualifiedName":"verbs.Monitor.Monitor","href":"verbs/Monitor/Monitor.html","type":"constructor","overriddenDepth":0,"packageName":"at_server_spec","enclosedBy":{"name":"Monitor","type":"class"}},{"name":"dependsOn","qualifiedName":"verbs.Monitor.dependsOn","href":"verbs/Monitor/dependsOn.html","type":"method","overriddenDepth":1,"packageName":"at_server_spec","enclosedBy":{"name":"Monitor","type":"class"}},{"name":"name","qualifiedName":"verbs.Monitor.name","href":"verbs/Monitor/name.html","type":"method","overriddenDepth":1,"packageName":"at_server_spec","enclosedBy":{"name":"Monitor","type":"class"}},{"name":"requiresAuth","qualifiedName":"verbs.Monitor.requiresAuth","href":"verbs/Monitor/requiresAuth.html","type":"method","overriddenDepth":1,"packageName":"at_server_spec","enclosedBy":{"name":"Monitor","type":"class"}},{"name":"syntax","qualifiedName":"verbs.Monitor.syntax","href":"verbs/Monitor/syntax.html","type":"method","overriddenDepth":1,"packageName":"at_server_spec","enclosedBy":{"name":"Monitor","type":"class"}},{"name":"usage","qualifiedName":"verbs.Monitor.usage","href":"verbs/Monitor/usage.html","type":"method","overriddenDepth":1,"packageName":"at_server_spec","enclosedBy":{"name":"Monitor","type":"class"}},{"name":"Notify","qualifiedName":"verbs.Notify","href":"verbs/Notify-class.html","type":"class","overriddenDepth":0,"packageName":"at_server_spec","enclosedBy":{"name":"verbs","type":"library"}},{"name":"Notify","qualifiedName":"verbs.Notify.Notify","href":"verbs/Notify/Notify.html","type":"constructor","overriddenDepth":0,"packageName":"at_server_spec","enclosedBy":{"name":"Notify","type":"class"}},{"name":"dependsOn","qualifiedName":"verbs.Notify.dependsOn","href":"verbs/Notify/dependsOn.html","type":"method","overriddenDepth":1,"packageName":"at_server_spec","enclosedBy":{"name":"Notify","type":"class"}},{"name":"name","qualifiedName":"verbs.Notify.name","href":"verbs/Notify/name.html","type":"method","overriddenDepth":1,"packageName":"at_server_spec","enclosedBy":{"name":"Notify","type":"class"}},{"name":"requiresAuth","qualifiedName":"verbs.Notify.requiresAuth","href":"verbs/Notify/requiresAuth.html","type":"method","overriddenDepth":1,"packageName":"at_server_spec","enclosedBy":{"name":"Notify","type":"class"}},{"name":"syntax","qualifiedName":"verbs.Notify.syntax","href":"verbs/Notify/syntax.html","type":"method","overriddenDepth":1,"packageName":"at_server_spec","enclosedBy":{"name":"Notify","type":"class"}},{"name":"usage","qualifiedName":"verbs.Notify.usage","href":"verbs/Notify/usage.html","type":"method","overriddenDepth":1,"packageName":"at_server_spec","enclosedBy":{"name":"Notify","type":"class"}},{"name":"NotifyList","qualifiedName":"verbs.NotifyList","href":"verbs/NotifyList-class.html","type":"class","overriddenDepth":0,"packageName":"at_server_spec","enclosedBy":{"name":"verbs","type":"library"}},{"name":"NotifyList","qualifiedName":"verbs.NotifyList.NotifyList","href":"verbs/NotifyList/NotifyList.html","type":"constructor","overriddenDepth":0,"packageName":"at_server_spec","enclosedBy":{"name":"NotifyList","type":"class"}},{"name":"dependsOn","qualifiedName":"verbs.NotifyList.dependsOn","href":"verbs/NotifyList/dependsOn.html","type":"method","overriddenDepth":1,"packageName":"at_server_spec","enclosedBy":{"name":"NotifyList","type":"class"}},{"name":"name","qualifiedName":"verbs.NotifyList.name","href":"verbs/NotifyList/name.html","type":"method","overriddenDepth":1,"packageName":"at_server_spec","enclosedBy":{"name":"NotifyList","type":"class"}},{"name":"requiresAuth","qualifiedName":"verbs.NotifyList.requiresAuth","href":"verbs/NotifyList/requiresAuth.html","type":"method","overriddenDepth":1,"packageName":"at_server_spec","enclosedBy":{"name":"NotifyList","type":"class"}},{"name":"syntax","qualifiedName":"verbs.NotifyList.syntax","href":"verbs/NotifyList/syntax.html","type":"method","overriddenDepth":1,"packageName":"at_server_spec","enclosedBy":{"name":"NotifyList","type":"class"}},{"name":"usage","qualifiedName":"verbs.NotifyList.usage","href":"verbs/NotifyList/usage.html","type":"method","overriddenDepth":1,"packageName":"at_server_spec","enclosedBy":{"name":"NotifyList","type":"class"}},{"name":"Pkam","qualifiedName":"verbs.Pkam","href":"verbs/Pkam-class.html","type":"class","overriddenDepth":0,"packageName":"at_server_spec","enclosedBy":{"name":"verbs","type":"library"}},{"name":"Pkam","qualifiedName":"verbs.Pkam.Pkam","href":"verbs/Pkam/Pkam.html","type":"constructor","overriddenDepth":0,"packageName":"at_server_spec","enclosedBy":{"name":"Pkam","type":"class"}},{"name":"dependsOn","qualifiedName":"verbs.Pkam.dependsOn","href":"verbs/Pkam/dependsOn.html","type":"method","overriddenDepth":1,"packageName":"at_server_spec","enclosedBy":{"name":"Pkam","type":"class"}},{"name":"name","qualifiedName":"verbs.Pkam.name","href":"verbs/Pkam/name.html","type":"method","overriddenDepth":1,"packageName":"at_server_spec","enclosedBy":{"name":"Pkam","type":"class"}},{"name":"requiresAuth","qualifiedName":"verbs.Pkam.requiresAuth","href":"verbs/Pkam/requiresAuth.html","type":"method","overriddenDepth":1,"packageName":"at_server_spec","enclosedBy":{"name":"Pkam","type":"class"}},{"name":"syntax","qualifiedName":"verbs.Pkam.syntax","href":"verbs/Pkam/syntax.html","type":"method","overriddenDepth":1,"packageName":"at_server_spec","enclosedBy":{"name":"Pkam","type":"class"}},{"name":"usage","qualifiedName":"verbs.Pkam.usage","href":"verbs/Pkam/usage.html","type":"method","overriddenDepth":1,"packageName":"at_server_spec","enclosedBy":{"name":"Pkam","type":"class"}},{"name":"Pol","qualifiedName":"verbs.Pol","href":"verbs/Pol-class.html","type":"class","overriddenDepth":0,"packageName":"at_server_spec","enclosedBy":{"name":"verbs","type":"library"}},{"name":"Pol","qualifiedName":"verbs.Pol.Pol","href":"verbs/Pol/Pol.html","type":"constructor","overriddenDepth":0,"packageName":"at_server_spec","enclosedBy":{"name":"Pol","type":"class"}},{"name":"dependsOn","qualifiedName":"verbs.Pol.dependsOn","href":"verbs/Pol/dependsOn.html","type":"method","overriddenDepth":1,"packageName":"at_server_spec","enclosedBy":{"name":"Pol","type":"class"}},{"name":"name","qualifiedName":"verbs.Pol.name","href":"verbs/Pol/name.html","type":"method","overriddenDepth":1,"packageName":"at_server_spec","enclosedBy":{"name":"Pol","type":"class"}},{"name":"requiresAuth","qualifiedName":"verbs.Pol.requiresAuth","href":"verbs/Pol/requiresAuth.html","type":"method","overriddenDepth":1,"packageName":"at_server_spec","enclosedBy":{"name":"Pol","type":"class"}},{"name":"syntax","qualifiedName":"verbs.Pol.syntax","href":"verbs/Pol/syntax.html","type":"method","overriddenDepth":1,"packageName":"at_server_spec","enclosedBy":{"name":"Pol","type":"class"}},{"name":"usage","qualifiedName":"verbs.Pol.usage","href":"verbs/Pol/usage.html","type":"method","overriddenDepth":1,"packageName":"at_server_spec","enclosedBy":{"name":"Pol","type":"class"}},{"name":"ProxyLookup","qualifiedName":"verbs.ProxyLookup","href":"verbs/ProxyLookup-class.html","type":"class","overriddenDepth":0,"packageName":"at_server_spec","enclosedBy":{"name":"verbs","type":"library"}},{"name":"ProxyLookup","qualifiedName":"verbs.ProxyLookup.ProxyLookup","href":"verbs/ProxyLookup/ProxyLookup.html","type":"constructor","overriddenDepth":0,"packageName":"at_server_spec","enclosedBy":{"name":"ProxyLookup","type":"class"}},{"name":"dependsOn","qualifiedName":"verbs.ProxyLookup.dependsOn","href":"verbs/ProxyLookup/dependsOn.html","type":"method","overriddenDepth":1,"packageName":"at_server_spec","enclosedBy":{"name":"ProxyLookup","type":"class"}},{"name":"name","qualifiedName":"verbs.ProxyLookup.name","href":"verbs/ProxyLookup/name.html","type":"method","overriddenDepth":1,"packageName":"at_server_spec","enclosedBy":{"name":"ProxyLookup","type":"class"}},{"name":"requiresAuth","qualifiedName":"verbs.ProxyLookup.requiresAuth","href":"verbs/ProxyLookup/requiresAuth.html","type":"method","overriddenDepth":1,"packageName":"at_server_spec","enclosedBy":{"name":"ProxyLookup","type":"class"}},{"name":"syntax","qualifiedName":"verbs.ProxyLookup.syntax","href":"verbs/ProxyLookup/syntax.html","type":"method","overriddenDepth":1,"packageName":"at_server_spec","enclosedBy":{"name":"ProxyLookup","type":"class"}},{"name":"usage","qualifiedName":"verbs.ProxyLookup.usage","href":"verbs/ProxyLookup/usage.html","type":"method","overriddenDepth":1,"packageName":"at_server_spec","enclosedBy":{"name":"ProxyLookup","type":"class"}},{"name":"Scan","qualifiedName":"verbs.Scan","href":"verbs/Scan-class.html","type":"class","overriddenDepth":0,"packageName":"at_server_spec","enclosedBy":{"name":"verbs","type":"library"}},{"name":"Scan","qualifiedName":"verbs.Scan.Scan","href":"verbs/Scan/Scan.html","type":"constructor","overriddenDepth":0,"packageName":"at_server_spec","enclosedBy":{"name":"Scan","type":"class"}},{"name":"dependsOn","qualifiedName":"verbs.Scan.dependsOn","href":"verbs/Scan/dependsOn.html","type":"method","overriddenDepth":1,"packageName":"at_server_spec","enclosedBy":{"name":"Scan","type":"class"}},{"name":"name","qualifiedName":"verbs.Scan.name","href":"verbs/Scan/name.html","type":"method","overriddenDepth":1,"packageName":"at_server_spec","enclosedBy":{"name":"Scan","type":"class"}},{"name":"requiresAuth","qualifiedName":"verbs.Scan.requiresAuth","href":"verbs/Scan/requiresAuth.html","type":"method","overriddenDepth":1,"packageName":"at_server_spec","enclosedBy":{"name":"Scan","type":"class"}},{"name":"syntax","qualifiedName":"verbs.Scan.syntax","href":"verbs/Scan/syntax.html","type":"method","overriddenDepth":1,"packageName":"at_server_spec","enclosedBy":{"name":"Scan","type":"class"}},{"name":"usage","qualifiedName":"verbs.Scan.usage","href":"verbs/Scan/usage.html","type":"method","overriddenDepth":1,"packageName":"at_server_spec","enclosedBy":{"name":"Scan","type":"class"}},{"name":"Stats","qualifiedName":"verbs.Stats","href":"verbs/Stats-class.html","type":"class","overriddenDepth":0,"packageName":"at_server_spec","enclosedBy":{"name":"verbs","type":"library"}},{"name":"Stats","qualifiedName":"verbs.Stats.Stats","href":"verbs/Stats/Stats.html","type":"constructor","overriddenDepth":0,"packageName":"at_server_spec","enclosedBy":{"name":"Stats","type":"class"}},{"name":"dependsOn","qualifiedName":"verbs.Stats.dependsOn","href":"verbs/Stats/dependsOn.html","type":"method","overriddenDepth":1,"packageName":"at_server_spec","enclosedBy":{"name":"Stats","type":"class"}},{"name":"name","qualifiedName":"verbs.Stats.name","href":"verbs/Stats/name.html","type":"method","overriddenDepth":1,"packageName":"at_server_spec","enclosedBy":{"name":"Stats","type":"class"}},{"name":"requiresAuth","qualifiedName":"verbs.Stats.requiresAuth","href":"verbs/Stats/requiresAuth.html","type":"method","overriddenDepth":1,"packageName":"at_server_spec","enclosedBy":{"name":"Stats","type":"class"}},{"name":"syntax","qualifiedName":"verbs.Stats.syntax","href":"verbs/Stats/syntax.html","type":"method","overriddenDepth":1,"packageName":"at_server_spec","enclosedBy":{"name":"Stats","type":"class"}},{"name":"usage","qualifiedName":"verbs.Stats.usage","href":"verbs/Stats/usage.html","type":"method","overriddenDepth":1,"packageName":"at_server_spec","enclosedBy":{"name":"Stats","type":"class"}},{"name":"StreamVerb","qualifiedName":"verbs.StreamVerb","href":"verbs/StreamVerb-class.html","type":"class","overriddenDepth":0,"packageName":"at_server_spec","enclosedBy":{"name":"verbs","type":"library"}},{"name":"StreamVerb","qualifiedName":"verbs.StreamVerb.StreamVerb","href":"verbs/StreamVerb/StreamVerb.html","type":"constructor","overriddenDepth":0,"packageName":"at_server_spec","enclosedBy":{"name":"StreamVerb","type":"class"}},{"name":"dependsOn","qualifiedName":"verbs.StreamVerb.dependsOn","href":"verbs/StreamVerb/dependsOn.html","type":"method","overriddenDepth":1,"packageName":"at_server_spec","enclosedBy":{"name":"StreamVerb","type":"class"}},{"name":"name","qualifiedName":"verbs.StreamVerb.name","href":"verbs/StreamVerb/name.html","type":"method","overriddenDepth":1,"packageName":"at_server_spec","enclosedBy":{"name":"StreamVerb","type":"class"}},{"name":"requiresAuth","qualifiedName":"verbs.StreamVerb.requiresAuth","href":"verbs/StreamVerb/requiresAuth.html","type":"method","overriddenDepth":1,"packageName":"at_server_spec","enclosedBy":{"name":"StreamVerb","type":"class"}},{"name":"syntax","qualifiedName":"verbs.StreamVerb.syntax","href":"verbs/StreamVerb/syntax.html","type":"method","overriddenDepth":1,"packageName":"at_server_spec","enclosedBy":{"name":"StreamVerb","type":"class"}},{"name":"usage","qualifiedName":"verbs.StreamVerb.usage","href":"verbs/StreamVerb/usage.html","type":"method","overriddenDepth":1,"packageName":"at_server_spec","enclosedBy":{"name":"StreamVerb","type":"class"}},{"name":"Sync","qualifiedName":"verbs.Sync","href":"verbs/Sync-class.html","type":"class","overriddenDepth":0,"packageName":"at_server_spec","enclosedBy":{"name":"verbs","type":"library"}},{"name":"Sync","qualifiedName":"verbs.Sync.Sync","href":"verbs/Sync/Sync.html","type":"constructor","overriddenDepth":0,"packageName":"at_server_spec","enclosedBy":{"name":"Sync","type":"class"}},{"name":"dependsOn","qualifiedName":"verbs.Sync.dependsOn","href":"verbs/Sync/dependsOn.html","type":"method","overriddenDepth":1,"packageName":"at_server_spec","enclosedBy":{"name":"Sync","type":"class"}},{"name":"name","qualifiedName":"verbs.Sync.name","href":"verbs/Sync/name.html","type":"method","overriddenDepth":1,"packageName":"at_server_spec","enclosedBy":{"name":"Sync","type":"class"}},{"name":"requiresAuth","qualifiedName":"verbs.Sync.requiresAuth","href":"verbs/Sync/requiresAuth.html","type":"method","overriddenDepth":1,"packageName":"at_server_spec","enclosedBy":{"name":"Sync","type":"class"}},{"name":"syntax","qualifiedName":"verbs.Sync.syntax","href":"verbs/Sync/syntax.html","type":"method","overriddenDepth":1,"packageName":"at_server_spec","enclosedBy":{"name":"Sync","type":"class"}},{"name":"usage","qualifiedName":"verbs.Sync.usage","href":"verbs/Sync/usage.html","type":"method","overriddenDepth":1,"packageName":"at_server_spec","enclosedBy":{"name":"Sync","type":"class"}},{"name":"Update","qualifiedName":"verbs.Update","href":"verbs/Update-class.html","type":"class","overriddenDepth":0,"packageName":"at_server_spec","enclosedBy":{"name":"verbs","type":"library"}},{"name":"Update","qualifiedName":"verbs.Update.Update","href":"verbs/Update/Update.html","type":"constructor","overriddenDepth":0,"packageName":"at_server_spec","enclosedBy":{"name":"Update","type":"class"}},{"name":"dependsOn","qualifiedName":"verbs.Update.dependsOn","href":"verbs/Update/dependsOn.html","type":"method","overriddenDepth":1,"packageName":"at_server_spec","enclosedBy":{"name":"Update","type":"class"}},{"name":"name","qualifiedName":"verbs.Update.name","href":"verbs/Update/name.html","type":"method","overriddenDepth":1,"packageName":"at_server_spec","enclosedBy":{"name":"Update","type":"class"}},{"name":"requiresAuth","qualifiedName":"verbs.Update.requiresAuth","href":"verbs/Update/requiresAuth.html","type":"method","overriddenDepth":1,"packageName":"at_server_spec","enclosedBy":{"name":"Update","type":"class"}},{"name":"syntax","qualifiedName":"verbs.Update.syntax","href":"verbs/Update/syntax.html","type":"method","overriddenDepth":1,"packageName":"at_server_spec","enclosedBy":{"name":"Update","type":"class"}},{"name":"usage","qualifiedName":"verbs.Update.usage","href":"verbs/Update/usage.html","type":"method","overriddenDepth":1,"packageName":"at_server_spec","enclosedBy":{"name":"Update","type":"class"}},{"name":"UpdateMeta","qualifiedName":"verbs.UpdateMeta","href":"verbs/UpdateMeta-class.html","type":"class","overriddenDepth":0,"packageName":"at_server_spec","enclosedBy":{"name":"verbs","type":"library"}},{"name":"UpdateMeta","qualifiedName":"verbs.UpdateMeta.UpdateMeta","href":"verbs/UpdateMeta/UpdateMeta.html","type":"constructor","overriddenDepth":0,"packageName":"at_server_spec","enclosedBy":{"name":"UpdateMeta","type":"class"}},{"name":"dependsOn","qualifiedName":"verbs.UpdateMeta.dependsOn","href":"verbs/UpdateMeta/dependsOn.html","type":"method","overriddenDepth":1,"packageName":"at_server_spec","enclosedBy":{"name":"UpdateMeta","type":"class"}},{"name":"name","qualifiedName":"verbs.UpdateMeta.name","href":"verbs/UpdateMeta/name.html","type":"method","overriddenDepth":1,"packageName":"at_server_spec","enclosedBy":{"name":"UpdateMeta","type":"class"}},{"name":"requiresAuth","qualifiedName":"verbs.UpdateMeta.requiresAuth","href":"verbs/UpdateMeta/requiresAuth.html","type":"method","overriddenDepth":1,"packageName":"at_server_spec","enclosedBy":{"name":"UpdateMeta","type":"class"}},{"name":"syntax","qualifiedName":"verbs.UpdateMeta.syntax","href":"verbs/UpdateMeta/syntax.html","type":"method","overriddenDepth":1,"packageName":"at_server_spec","enclosedBy":{"name":"UpdateMeta","type":"class"}},{"name":"usage","qualifiedName":"verbs.UpdateMeta.usage","href":"verbs/UpdateMeta/usage.html","type":"method","overriddenDepth":1,"packageName":"at_server_spec","enclosedBy":{"name":"UpdateMeta","type":"class"}},{"name":"Verb","qualifiedName":"verbs.Verb","href":"verbs/Verb-class.html","type":"class","overriddenDepth":0,"packageName":"at_server_spec","enclosedBy":{"name":"verbs","type":"library"}},{"name":"Verb","qualifiedName":"verbs.Verb.Verb","href":"verbs/Verb/Verb.html","type":"constructor","overriddenDepth":0,"packageName":"at_server_spec","enclosedBy":{"name":"Verb","type":"class"}},{"name":"dependsOn","qualifiedName":"verbs.Verb.dependsOn","href":"verbs/Verb/dependsOn.html","type":"method","overriddenDepth":0,"packageName":"at_server_spec","enclosedBy":{"name":"Verb","type":"class"}},{"name":"name","qualifiedName":"verbs.Verb.name","href":"verbs/Verb/name.html","type":"method","overriddenDepth":0,"packageName":"at_server_spec","enclosedBy":{"name":"Verb","type":"class"}},{"name":"requiresAuth","qualifiedName":"verbs.Verb.requiresAuth","href":"verbs/Verb/requiresAuth.html","type":"method","overriddenDepth":0,"packageName":"at_server_spec","enclosedBy":{"name":"Verb","type":"class"}},{"name":"syntax","qualifiedName":"verbs.Verb.syntax","href":"verbs/Verb/syntax.html","type":"method","overriddenDepth":0,"packageName":"at_server_spec","enclosedBy":{"name":"Verb","type":"class"}},{"name":"usage","qualifiedName":"verbs.Verb.usage","href":"verbs/Verb/usage.html","type":"method","overriddenDepth":0,"packageName":"at_server_spec","enclosedBy":{"name":"Verb","type":"class"}}]
